Workbook

Sheet Summary
A1: May 2026 Financial Statements
A2: Updated June 9, 2026. Invite-related expenses are now included in expense.
A4: Net Income | C4: Dividend To Record
A5: =Income Statement!C20 -> 37337.121 | C5: =Equity Rollforward!C8 -> 51890.611
A7: Closing Equity | C7: User Balances
A8: =Equity Rollforward!C9 -> 120000 | C8: =Balance Sheet!C9 -> 145063.7
A11: Expense Update | D11: Month-End Cash Basis
A12: Original adjusted expense | B12: 53932.78 | D12: If dividend payable | E12: =Balance Sheet!C5 -> 316954.31
A13: Added invite-related expense | B13: =Assumptions!B12+Assumptions!B13+Assumptions!B14 -> 1153.1389 | D13: If dividend already paid | E13: =Balance Sheet!C6 -> 265063.7
A14: Updated total expense | B14: =Income Statement!C19 -> 55085.919 | D14: Dividend payable | E14: =Balance Sheet!C10 -> 51890.611
A15: Updated net income | B15: =Income Statement!C20 -> 37337.121
A18: Invite expense components included in expense
A19: Reason | B19: Count | C19: Amount
A20: 邀请返现（打赏） | B20: 957 | C20: 771.6389
A21: 邀请返现（订单） | B21: 160 | C21: 201.5
A22: 邀请奖励（进服） | B22: 90 | C22: 180
A23: Total | B23: =SUM(B20:B22) -> 1207 | C23: =SUM(C20:C22) -> 1153.1389

Sheet Assumptions
A1: Assumptions & Inputs
A2: Manual opening balance plus May DB and off-DB adjustments.
A4: Category | B4: Amount / Value | C4: Count | D4: Notes
A5: Revenue total | B5: 92423.04 | D5: DB revenue total for May 2026
A6: Commission net | B6: 86109.35
A7: Lottery net | B7: 967.65
A8: Scratch net | B8: 1202
A9: Block Stack net | B9: 1269.91
A10: PureProfit / manual income adjustment | B10: 2874.13
A11: Base DB expense | B11: 12857.48 | D11: Expense table only
A12: Invite expense - gift referral | B12: 771.6389 | C12: 957 | D12: Net payouts after revert adjustments
A13: Invite expense - order referral | B13: 201.5 | C13: 160 | D13: ReferralPayout linked to ended orders
A14: Invite expense - join reward | B14: 180 | C14: 90 | D14: InviteLinkUsage rewards
A15: Off-DB expense | B15: 41075.3 | D15: User-provided manual expenses
A16: Opening equity | B16: 134553.49 | D16: 2026-05-04 04:09 Toronto
A17: Initial capital | B17: 120000 | D17: Target closing equity after dividend
A18: Month-end user balances | B18: 145063.7 | D18: Excludes 锦鲤小助手
A19: Helper account excluded | B19: 1441310169492361268 | D19: 锦鲤小助手
A20: Closing cutoff | B20: 2026-06-01 00:00 Europe/Rome | D20: Balance sheet date basis

Sheet OffDB Detail
A1: Off-DB Expense Detail
A2: User-supplied expenses not recorded in the database.
A4: # | B4: Description | C4: Amount
A5: 1 | B5: zpay | C5: 500
A6: 2 | B6: 提现 | C6: 6
A7: 3 | B7: 冰心 | C7: 200
A8: 4 | B8: 提现 | C8: 7
A9: 5 | B9: zpay | C9: 500
A10: 6 | B10: 做饭/白图 | C10: 300
A11: 7 | B11: canva | C11: 115.7
A12: 8 | B12: nitro | C12: 280
A13: 9 | B13: csgo hub | C13: 2488
A14: 10 | B14: yoki做图 | C14: 3060
A15: 11 | B15: 520活动策划 | C15: 350
A16: 12 | B16: 4月服务器 | C16: 354
... A35: 31 | B35: 5月服务器 | C35: 357
A36: Total | C36: =SUM(C5:C35) -> 41075.3

Sheet Income Statement
A1: Income Statement
A2: May 2026, including invite-related expense categories.
A4: Line Item | B4: Count | C4: Amount | D4: Notes
A5: Revenue
A6: Commission net | C6: =Assumptions!B6 -> 86109.35
A7: Lottery net | C7: =Assumptions!B7 -> 967.65
A8: Scratch net | C8: =Assumptions!B8 -> 1202
A9: Block Stack net | C9: =Assumptions!B9 -> 1269.91
A10: PureProfit / manual income adjustment | C10: =Assumptions!B10 -> 2874.13
A11: Total revenue | C11: =SUM(C6:C10) -> 92423.04
A13: Expenses
A14: DB expense (Expense table) | C14: =Assumptions!B11 -> 12857.48 | D14: Original DB expense bucket
A15: 邀请返现（打赏） | B15: =Assumptions!C12 -> 957 | C15: =Assumptions!B12 -> 771.6389 | D15: Net of reverted gift referrals
A16: 邀请返现（订单） | B16: =Assumptions!C13 -> 160 | C16: =Assumptions!B13 -> 201.5 | D16: ReferralPayout linked to ended orders
A17: 邀请奖励（进服） | B17: =Assumptions!C14 -> 90 | C17: =Assumptions!B14 -> 180 | D17: InviteLinkUsage reward payouts
A18: Off-DB expense | C18: =Assumptions!B15 -> 41075.3 | D18: Manual operating expenses
A19: Total expense | C19: =SUM(C14:C18) -> 55085.919
A20: Net income | C20: =C11-C19 -> 37337.121

Sheet Equity Rollforward
A1: Equity Rollforward
A2: Opening equity plus May net income, then reduced to initial capital via dividend.
A4: Line Item | B4: Formula / Basis | C4: Amount | D4: Notes
A5: Opening equity | B5: Manual opening record | C5: =Assumptions!B16 -> 134553.49 | D5: 2026-05-04 04:09 Toronto
A6: Add: May net income | B6: Income Statement | C6: =Income Statement!C20 -> 37337.121 | D6: Includes invite-related expense
A7: Equity before dividend | C7: =C5+C6 -> 171890.61
A8: Less: dividend to record | B8: Cap equity at initial capital | C8: =MAX(C7-Assumptions!B17,0) -> 51890.611
A9: Closing equity | C9: =C7-C8 -> 120000 | D9: Should equal initial capital

Sheet Balance Sheet
A1: Balance Sheet
A2: May 31, 2026 month-end basis.
A4: Line Item | B4: Scenario | C4: Amount | D4: Notes
A5: Cash | B5: If dividend payable | C5: =Assumptions!B18+Equity Rollforward!C8+Equity Rollforward!C9 -> 316954.31
A6: Cash | B6: If dividend already paid | C6: =Assumptions!B18+Equity Rollforward!C9 -> 265063.7
A8: Liabilities
A9: User balances | C9: =Assumptions!B18 -> 145063.7 | D9: Excludes 锦鲤小助手
A10: Dividend payable | C10: =Equity Rollforward!C8 -> 51890.611 | D10: Only if unpaid at month-end
A12: Equity
A13: Closing equity | C13: =Equity Rollforward!C9 -> 120000 | D13: Targeted back to initial capital

Sheet Checks
A1: Checks
A2: Key tie-outs for the updated May 2026 statements.
A4: Check | B4: Actual | C4: Expected | D4: Difference | E4: Status
A5: Income statement total revenue tie | B5: =Income Statement!C11 -> 92423.04 | C5: =Assumptions!B5 -> 92423.04 | D5: =B5-C5 -> 0 | E5: =IF(ABS(D5)<0.005,"OK","CHECK") -> OK
A6: Income statement total expense tie | B6: =Income Statement!C19 -> 55085.919 | C6: =Assumptions!B11+Assumptions!B12+Assumptions!B13+Assumptions!B14+Assumptions!B15 -> 55085.919 | D6: =B6-C6 -> 0 | E6: =IF(ABS(D6)<0.005,"OK","CHECK") -> OK
A7: Closing equity equals initial capital | B7: =Equity Rollforward!C9 -> 120000 | C7: =Assumptions!B17 -> 120000 | D7: =B7-C7 -> 0 | E7: =IF(ABS(D7)<0.005,"OK","CHECK") -> OK
A8: Balance sheet payable basis balances | B8: =Balance Sheet!C5 -> 316954.31 | C8: =Balance Sheet!C9+Balance Sheet!C10+Balance Sheet!C13 -> 316954.31 | D8: =B8-C8 -> 0 | E8: =IF(ABS(D8)<0.005,"OK","CHECK") -> OK
A9: Balance sheet paid basis balances | B9: =Balance Sheet!C6 -> 265063.7 | C9: =Balance Sheet!C9+Balance Sheet!C13 -> 265063.7 | D9: =B9-C9 -> 0 | E9: =IF(ABS(D9)<0.005,"OK","CHECK") -> OK
